README.md
setup.cfg
setup.py
pyOpenBCI/__init__.py
pyOpenBCI/cyton.py
pyOpenBCI/ganglion.py
pyOpenBCI/wifi.py
pyOpenBCI.egg-info/PKG-INFO
pyOpenBCI.egg-info/SOURCES.txt
pyOpenBCI.egg-info/dependency_links.txt
pyOpenBCI.egg-info/top_level.txt
pyOpenBCI/utils/__init__.py
pyOpenBCI/utils/ssdp.py