Metadata-Version: 2.1
Name: pyOpenBCI
Version: 0.12
Summary: A lib for controlling OpenBCI devices
Home-page: https://github.com/andreaortuno/pyOpenBCI
Author: OpenBCI, Inc.
Author-email: contact@openbci.com
License: MIT
Download-URL: https://github.com/andreaortuno/pyOpenBCI/archive/0.12.tar.gz
Keywords: device,control,eeg,emg,ekg,ads1299,openbci,ganglion,cyton,wifi
Platform: UNKNOWN
Classifier: Development Status :: 3 - Alpha
Classifier: Intended Audience :: Developers
Classifier: Topic :: Software Development :: Build Tools
Classifier: License :: OSI Approved :: MIT License
Classifier: Programming Language :: Python :: 3
Classifier: Programming Language :: Python :: 2.7
Classifier: Programming Language :: Python :: 3.4
Classifier: Programming Language :: Python :: 3.6
